log_parser/__init__.py
log_parser/aggregation.py
log_parser/config.py
log_parser/construct_api.py
log_parser/excp.py
log_parser/fields.py
log_parser/handlers.py
log_parser/loader.py
log_parser/log_formats.py
log_parser/module.py
log_parser/module_main.py
log_parser/parser.py
log_parser/server.py
log_parser/service.py
log_parser/template.py
log_parser/yaml_adapter.py
log_parser/default.conf/api.json
log_parser/default.conf/config.yml
log_parser/default.conf/log_formats.yml
log_parser/default.conf/report.yml
log_parser/default.conf/templates/50mounted-tests.yml
log_parser/default.conf/templates/FFPROXY.yml
log_parser/default.conf/templates/ModemManager.yml
log_parser/default.conf/templates/NetworkManager.yml
log_parser/default.conf/templates/Tor.yml
log_parser/default.conf/templates/acpid.yml
log_parser/default.conf/templates/anacron.yml
log_parser/default.conf/templates/apache.yml
log_parser/default.conf/templates/apache2.yml
log_parser/default.conf/templates/audispd.yml
log_parser/default.conf/templates/auditd.yml
log_parser/default.conf/templates/auth.yml
log_parser/default.conf/templates/bluetooth.yml
log_parser/default.conf/templates/certbot.yml
log_parser/default.conf/templates/cinnamon.yml
log_parser/default.conf/templates/colord.yml
log_parser/default.conf/templates/console-kit-daemon.yml
log_parser/default.conf/templates/cron.yml
log_parser/default.conf/templates/danted.yml
log_parser/default.conf/templates/dbus.yml
log_parser/default.conf/templates/dhclient.yml
log_parser/default.conf/templates/dhcpd.yml
log_parser/default.conf/templates/dnsmasq.yml
log_parser/default.conf/templates/dovecot.yml
log_parser/default.conf/templates/exim4.yml
log_parser/default.conf/templates/fail2ban.yml
log_parser/default.conf/templates/filesystem.yml
log_parser/default.conf/templates/ifup.yml
log_parser/default.conf/templates/influxd.yml
log_parser/default.conf/templates/kernel.yml
log_parser-2.3.dist-info/METADATA
log_parser-2.3.dist-info/RECORD
log_parser-2.3.dist-info/WHEEL
log_parser-2.3.dist-info/top_level.txt
